wallarmrasp/__init__.py
wallarmrasp/sessionmanager.py
wallarmrasp/stream.py
wallarmrasp/wallarmrasp.py
wallarmrasp-0.0.5.dist-info/LICENSE
wallarmrasp-0.0.5.dist-info/METADATA
wallarmrasp-0.0.5.dist-info/WHEEL
wallarmrasp-0.0.5.dist-info/top_level.txt
wallarmrasp-0.0.5.dist-info/RECORD
